{
  "openapi": "3.0.1",
  "info": {
    "title": "SistemaEducativoADB.API2",
    "version": "1.0"
  },
  "paths": {
    "/api/Asistencia": {
      "get": {
        "tags": [
          "Asistencia"
        ],
        "responses": {
          "200": {
            "description": "OK"
          }
        }
      },
      "post": {
        "tags": [
          "Asistencia"
        ],
        "requestBody": {
          "content": {
            "application/json": {
              "schema": {
                "$ref": "#/components/schemas/AsistenciaCreateDto"
              }
            },
            "text/json": {
              "schema": {
                "$ref": "#/components/schemas/AsistenciaCreateDto"
              }
            },
            "application/*+json": {
              "schema": {
                "$ref": "#/components/schemas/AsistenciaCreateDto"
              }
            }
          }
        },
        "responses": {
          "200": {
            "description": "OK"
          }
        }
      }
    },
    "/api/Asistencia/{id}": {
      "get": {
        "tags": [
          "Asistencia"
        ],
        "parameters": [
          {
            "name": "id",
            "in": "path",
            "required": true,
            "schema": {
              "type": "integer",
              "format": "int32"
            }
          }
        ],
        "responses": {
          "200": {
            "description": "OK"
          }
        }
      },
      "put": {
        "tags": [
          "Asistencia"
        ],
        "parameters": [
          {
            "name": "id",
            "in": "path",
            "required": true,
            "schema": {
              "type": "integer",
              "format": "int32"
            }
          }
        ],
        "requestBody": {
          "content": {
            "application/json": {
              "schema": {
                "$ref": "#/components/schemas/Asistencia"
              }
            },
            "text/json": {
              "schema": {
                "$ref": "#/components/schemas/Asistencia"
              }
            },
            "application/*+json": {
              "schema": {
                "$ref": "#/components/schemas/Asistencia"
              }
            }
          }
        },
        "responses": {
          "200": {
            "description": "OK"
          }
        }
      },
      "delete": {
        "tags": [
          "Asistencia"
        ],
        "parameters": [
          {
            "name": "id",
            "in": "path",
            "required": true,
            "schema": {
              "type": "integer",
              "format": "int32"
            }
          }
        ],
        "responses": {
          "200": {
            "description": "OK"
          }
        }
      }
    },
    "/api/Bitacoras": {
      "get": {
        "tags": [
          "Bitacoras"
        ],
        "responses": {
          "200": {
            "description": "OK"
          }
        }
      },
      "post": {
        "tags": [
          "Bitacoras"
        ],
        "requestBody": {
          "content": {
            "application/json": {
              "schema": {
                "$ref": "#/components/schemas/BitacoraCreateDto"
              }
            },
            "text/json": {
              "schema": {
                "$ref": "#/components/schemas/BitacoraCreateDto"
              }
            },
            "application/*+json": {
              "schema": {
                "$ref": "#/components/schemas/BitacoraCreateDto"
              }
            }
          }
        },
        "responses": {
          "200": {
            "description": "OK"
          }
        }
      }
    },
    "/api/Bitacoras/{id}": {
      "get": {
        "tags": [
          "Bitacoras"
        ],
        "parameters": [
          {
            "name": "id",
            "in": "path",
            "required": true,
            "schema": {
              "type": "integer",
              "format": "int32"
            }
          }
        ],
        "responses": {
          "200": {
            "description": "OK"
          }
        }
      },
      "delete": {
        "tags": [
          "Bitacoras"
        ],
        "parameters": [
          {
            "name": "id",
            "in": "path",
            "required": true,
            "schema": {
              "type": "integer",
              "format": "int32"
            }
          }
        ],
        "responses": {
          "200": {
            "description": "OK"
          }
        }
      }
    },
    "/api/Carreras": {
      "get": {
        "tags": [
          "Carreras"
        ],
        "responses": {
          "200": {
            "description": "OK"
          }
        }
      },
      "post": {
        "tags": [
          "Carreras"
        ],
        "requestBody": {
          "content": {
            "application/json": {
              "schema": {
                "$ref": "#/components/schemas/CarreraCreateDto"
              }
            },
            "text/json": {
              "schema": {
                "$ref": "#/components/schemas/CarreraCreateDto"
              }
            },
            "application/*+json": {
              "schema": {
                "$ref": "#/components/schemas/CarreraCreateDto"
              }
            }
          }
        },
        "responses": {
          "200": {
            "description": "OK"
          }
        }
      }
    },
    "/api/Carreras/{id}": {
      "get": {
        "tags": [
          "Carreras"
        ],
        "parameters": [
          {
            "name": "id",
            "in": "path",
            "required": true,
            "schema": {
              "type": "integer",
              "format": "int32"
            }
          }
        ],
        "responses": {
          "200": {
            "description": "OK"
          }
        }
      },
      "put": {
        "tags": [
          "Carreras"
        ],
        "parameters": [
          {
            "name": "id",
            "in": "path",
            "required": true,
            "schema": {
              "type": "integer",
              "format": "int32"
            }
          }
        ],
        "requestBody": {
          "content": {
            "application/json": {
              "schema": {
                "$ref": "#/components/schemas/Carrera"
              }
            },
            "text/json": {
              "schema": {
                "$ref": "#/components/schemas/Carrera"
              }
            },
            "application/*+json": {
              "schema": {
                "$ref": "#/components/schemas/Carrera"
              }
            }
          }
        },
        "responses": {
          "200": {
            "description": "OK"
          }
        }
      },
      "delete": {
        "tags": [
          "Carreras"
        ],
        "parameters": [
          {
            "name": "id",
            "in": "path",
            "required": true,
            "schema": {
              "type": "integer",
              "format": "int32"
            }
          }
        ],
        "responses": {
          "200": {
            "description": "OK"
          }
        }
      }
    },
    "/api/Cita_Matriculas": {
      "get": {
        "tags": [
          "Cita_Matriculas"
        ],
        "responses": {
          "200": {
            "description": "OK"
          }
        }
      },
      "post": {
        "tags": [
          "Cita_Matriculas"
        ],
        "requestBody": {
          "content": {
            "application/json": {
              "schema": {
                "$ref": "#/components/schemas/CitaMatriculaCreateDto"
              }
            },
            "text/json": {
              "schema": {
                "$ref": "#/components/schemas/CitaMatriculaCreateDto"
              }
            },
            "application/*+json": {
              "schema": {
                "$ref": "#/components/schemas/CitaMatriculaCreateDto"
              }
            }
          }
        },
        "responses": {
          "200": {
            "description": "OK"
          }
        }
      }
    },
    "/api/Cita_Matriculas/{id}": {
      "get": {
        "tags": [
          "Cita_Matriculas"
        ],
        "parameters": [
          {
            "name": "id",
            "in": "path",
            "required": true,
            "schema": {
              "type": "integer",
              "format": "int32"
            }
          }
        ],
        "responses": {
          "200": {
            "description": "OK"
          }
        }
      },
      "put": {
        "tags": [
          "Cita_Matriculas"
        ],
        "parameters": [
          {
            "name": "id",
            "in": "path",
            "required": true,
            "schema": {
              "type": "integer",
              "format": "int32"
            }
          }
        ],
        "requestBody": {
          "content": {
            "application/json": {
              "schema": {
                "$ref": "#/components/schemas/Cita_Matricula"
              }
            },
            "text/json": {
              "schema": {
                "$ref": "#/components/schemas/Cita_Matricula"
              }
            },
            "application/*+json": {
              "schema": {
                "$ref": "#/components/schemas/Cita_Matricula"
              }
            }
          }
        },
        "responses": {
          "200": {
            "description": "OK"
          }
        }
      },
      "delete": {
        "tags": [
          "Cita_Matriculas"
        ],
        "parameters": [
          {
            "name": "id",
            "in": "path",
            "required": true,
            "schema": {
              "type": "integer",
              "format": "int32"
            }
          }
        ],
        "responses": {
          "200": {
            "description": "OK"
          }
        }
      }
    },
    "/api/Correquisitos": {
      "get": {
        "tags": [
          "Correquisitos"
        ],
        "responses": {
          "200": {
            "description": "OK"
          }
        }
      },
      "post": {
        "tags": [
          "Correquisitos"
        ],
        "requestBody": {
          "content": {
            "application/json": {
              "schema": {
                "$ref": "#/components/schemas/CorrequisitoCreateDto"
              }
            },
            "text/json": {
              "schema": {
                "$ref": "#/components/schemas/CorrequisitoCreateDto"
              }
            },
            "application/*+json": {
              "schema": {
                "$ref": "#/components/schemas/CorrequisitoCreateDto"
              }
            }
          }
        },
        "responses": {
          "200": {
            "description": "OK"
          }
        }
      }
    },
    "/api/Correquisitos/{id}": {
      "get": {
        "tags": [
          "Correquisitos"
        ],
        "parameters": [
          {
            "name": "id",
            "in": "path",
            "required": true,
            "schema": {
              "type": "integer",
              "format": "int32"
            }
          }
        ],
        "responses": {
          "200": {
            "description": "OK"
          }
        }
      },
      "put": {
        "tags": [
          "Correquisitos"
        ],
        "parameters": [
          {
            "name": "id",
            "in": "path",
            "required": true,
            "schema": {
              "type": "integer",
              "format": "int32"
            }
          }
        ],
        "requestBody": {
          "content": {
            "application/json": {
              "schema": {
                "$ref": "#/components/schemas/Correquisito"
              }
            },
            "text/json": {
              "schema": {
                "$ref": "#/components/schemas/Correquisito"
              }
            },
            "application/*+json": {
              "schema": {
                "$ref": "#/components/schemas/Correquisito"
              }
            }
          }
        },
        "responses": {
          "200": {
            "description": "OK"
          }
        }
      },
      "delete": {
        "tags": [
          "Correquisitos"
        ],
        "parameters": [
          {
            "name": "id",
            "in": "path",
            "required": true,
            "schema": {
              "type": "integer",
              "format": "int32"
            }
          }
        ],
        "responses": {
          "200": {
            "description": "OK"
          }
        }
      }
    },
    "/api/Detalle_Matriculas": {
      "get": {
        "tags": [
          "Detalle_Matriculas"
        ],
        "responses": {
          "200": {
            "description": "OK"
          }
        }
      },
      "post": {
        "tags": [
          "Detalle_Matriculas"
        ],
        "requestBody": {
          "content": {
            "application/json": {
              "schema": {
                "$ref": "#/components/schemas/Detalle_MatriculaCreateDto"
              }
            },
            "text/json": {
              "schema": {
                "$ref": "#/components/schemas/Detalle_MatriculaCreateDto"
              }
            },
            "application/*+json": {
              "schema": {
                "$ref": "#/components/schemas/Detalle_MatriculaCreateDto"
              }
            }
          }
        },
        "responses": {
          "200": {
            "description": "OK"
          }
        }
      }
    },
    "/api/Detalle_Matriculas/{id}": {
      "get": {
        "tags": [
          "Detalle_Matriculas"
        ],
        "parameters": [
          {
            "name": "id",
            "in": "path",
            "required": true,
            "schema": {
              "type": "integer",
              "format": "int32"
            }
          }
        ],
        "responses": {
          "200": {
            "description": "OK"
          }
        }
      },
      "put": {
        "tags": [
          "Detalle_Matriculas"
        ],
        "parameters": [
          {
            "name": "id",
            "in": "path",
            "required": true,
            "schema": {
              "type": "integer",
              "format": "int32"
            }
          }
        ],
        "requestBody": {
          "content": {
            "application/json": {
              "schema": {
                "$ref": "#/components/schemas/Detalle_Matricula"
              }
            },
            "text/json": {
              "schema": {
                "$ref": "#/components/schemas/Detalle_Matricula"
              }
            },
            "application/*+json": {
              "schema": {
                "$ref": "#/components/schemas/Detalle_Matricula"
              }
            }
          }
        },
        "responses": {
          "200": {
            "description": "OK"
          }
        }
      },
      "delete": {
        "tags": [
          "Detalle_Matriculas"
        ],
        "parameters": [
          {
            "name": "id",
            "in": "path",
            "required": true,
            "schema": {
              "type": "integer",
              "format": "int32"
            }
          }
        ],
        "responses": {
          "200": {
            "description": "OK"
          }
        }
      }
    },
    "/api/Detalle_Pagos": {
      "get": {
        "tags": [
          "Detalle_Pagos"
        ],
        "responses": {
          "200": {
            "description": "OK"
          }
        }
      },
      "post": {
        "tags": [
          "Detalle_Pagos"
        ],
        "requestBody": {
          "content": {
            "application/json": {
              "schema": {
                "$ref": "#/components/schemas/Detalle_PagosCreateDto"
              }
            },
            "text/json": {
              "schema": {
                "$ref": "#/components/schemas/Detalle_PagosCreateDto"
              }
            },
            "application/*+json": {
              "schema": {
                "$ref": "#/components/schemas/Detalle_PagosCreateDto"
              }
            }
          }
        },
        "responses": {
          "200": {
            "description": "OK"
          }
        }
      }
    },
    "/api/Detalle_Pagos/{id}": {
      "get": {
        "tags": [
          "Detalle_Pagos"
        ],
        "parameters": [
          {
            "name": "id",
            "in": "path",
            "required": true,
            "schema": {
              "type": "integer",
              "format": "int32"
            }
          }
        ],
        "responses": {
          "200": {
            "description": "OK"
          }
        }
      },
      "put": {
        "tags": [
          "Detalle_Pagos"
        ],
        "parameters": [
          {
            "name": "id",
            "in": "path",
            "required": true,
            "schema": {
              "type": "integer",
              "format": "int32"
            }
          }
        ],
        "requestBody": {
          "content": {
            "application/json": {
              "schema": {
                "$ref": "#/components/schemas/DetallePago"
              }
            },
            "text/json": {
              "schema": {
                "$ref": "#/components/schemas/DetallePago"
              }
            },
            "application/*+json": {
              "schema": {
                "$ref": "#/components/schemas/DetallePago"
              }
            }
          }
        },
        "responses": {
          "200": {
            "description": "OK"
          }
        }
      },
      "delete": {
        "tags": [
          "Detalle_Pagos"
        ],
        "parameters": [
          {
            "name": "id",
            "in": "path",
            "required": true,
            "schema": {
              "type": "integer",
              "format": "int32"
            }
          }
        ],
        "responses": {
          "200": {
            "description": "OK"
          }
        }
      }
    },
    "/api/Detalle_Pagos/PorPago/{id_pago}": {
      "get": {
        "tags": [
          "Detalle_Pagos"
        ],
        "parameters": [
          {
            "name": "id_pago",
            "in": "path",
            "required": true,
            "schema": {
              "type": "integer",
              "format": "int32"
            }
          }
        ],
        "responses": {
          "200": {
            "description": "OK"
          }
        }
      }
    },
    "/api/Detalle_Pagos/PorMatricula/{id_matricula}": {
      "get": {
        "tags": [
          "Detalle_Pagos"
        ],
        "parameters": [
          {
            "name": "id_matricula",
            "in": "path",
            "required": true,
            "schema": {
              "type": "integer",
              "format": "int32"
            }
          }
        ],
        "responses": {
          "200": {
            "description": "OK"
          }
        }
      }
    },
    "/api/Estudiantes": {
      "get": {
        "tags": [
          "Estudiantes"
        ],
        "responses": {
          "200": {
            "description": "OK"
          }
        }
      },
      "post": {
        "tags": [
          "Estudiantes"
        ],
        "requestBody": {
          "content": {
            "application/json": {
              "schema": {
                "$ref": "#/components/schemas/EstudianteCreateDto"
              }
            },
            "text/json": {
              "schema": {
                "$ref": "#/components/schemas/EstudianteCreateDto"
              }
            },
            "application/*+json": {
              "schema": {
                "$ref": "#/components/schemas/EstudianteCreateDto"
              }
            }
          }
        },
        "responses": {
          "200": {
            "description": "OK"
          }
        }
      }
    },
    "/api/Estudiantes/{id}": {
      "get": {
        "tags": [
          "Estudiantes"
        ],
        "parameters": [
          {
            "name": "id",
            "in": "path",
            "required": true,
            "schema": {
              "type": "integer",
              "format": "int32"
            }
          }
        ],
        "responses": {
          "200": {
            "description": "OK"
          }
        }
      },
      "put": {
        "tags": [
          "Estudiantes"
        ],
        "parameters": [
          {
            "name": "id",
            "in": "path",
            "required": true,
            "schema": {
              "type": "integer",
              "format": "int32"
            }
          }
        ],
        "requestBody": {
          "content": {
            "application/json": {
              "schema": {
                "$ref": "#/components/schemas/Estudiante"
              }
            },
            "text/json": {
              "schema": {
                "$ref": "#/components/schemas/Estudiante"
              }
            },
            "application/*+json": {
              "schema": {
                "$ref": "#/components/schemas/Estudiante"
              }
            }
          }
        },
        "responses": {
          "200": {
            "description": "OK"
          }
        }
      },
      "delete": {
        "tags": [
          "Estudiantes"
        ],
        "parameters": [
          {
            "name": "id",
            "in": "path",
            "required": true,
            "schema": {
              "type": "integer",
              "format": "int32"
            }
          }
        ],
        "responses": {
          "200": {
            "description": "OK"
          }
        }
      }
    },
    "/api/Grupos": {
      "get": {
        "tags": [
          "Grupos"
        ],
        "responses": {
          "200": {
            "description": "OK"
          }
        }
      },
      "post": {
        "tags": [
          "Grupos"
        ],
        "requestBody": {
          "content": {
            "application/json": {
              "schema": {
                "$ref": "#/components/schemas/GruposCreateDto"
              }
            },
            "text/json": {
              "schema": {
                "$ref": "#/components/schemas/GruposCreateDto"
              }
            },
            "application/*+json": {
              "schema": {
                "$ref": "#/components/schemas/GruposCreateDto"
              }
            }
          }
        },
        "responses": {
          "200": {
            "description": "OK"
          }
        }
      }
    },
    "/api/Grupos/{id}": {
      "get": {
        "tags": [
          "Grupos"
        ],
        "parameters": [
          {
            "name": "id",
            "in": "path",
            "required": true,
            "schema": {
              "type": "integer",
              "format": "int32"
            }
          }
        ],
        "responses": {
          "200": {
            "description": "OK"
          }
        }
      },
      "put": {
        "tags": [
          "Grupos"
        ],
        "parameters": [
          {
            "name": "id",
            "in": "path",
            "required": true,
            "schema": {
              "type": "integer",
              "format": "int32"
            }
          }
        ],
        "requestBody": {
          "content": {
            "application/json": {
              "schema": {
                "$ref": "#/components/schemas/GrupoPutBody"
              }
            },
            "text/json": {
              "schema": {
                "$ref": "#/components/schemas/GrupoPutBody"
              }
            },
            "application/*+json": {
              "schema": {
                "$ref": "#/components/schemas/GrupoPutBody"
              }
            }
          }
        },
        "responses": {
          "200": {
            "description": "OK"
          }
        }
      },
      "delete": {
        "tags": [
          "Grupos"
        ],
        "parameters": [
          {
            "name": "id",
            "in": "path",
            "required": true,
            "schema": {
              "type": "integer",
              "format": "int32"
            }
          }
        ],
        "responses": {
          "200": {
            "description": "OK"
          }
        }
      }
    },
    "/api/Grupos/PorMateria/{id_materia}": {
      "get": {
        "tags": [
          "Grupos"
        ],
        "parameters": [
          {
            "name": "id_materia",
            "in": "path",
            "required": true,
            "schema": {
              "type": "integer",
              "format": "int32"
            }
          }
        ],
        "responses": {
          "200": {
            "description": "OK"
          }
        }
      }
    },
    "/api/Grupos/PorProfesor/{id_profesor}": {
      "get": {
        "tags": [
          "Grupos"
        ],
        "parameters": [
          {
            "name": "id_profesor",
            "in": "path",
            "required": true,
            "schema": {
              "type": "integer",
              "format": "int32"
            }
          }
        ],
        "responses": {
          "200": {
            "description": "OK"
          }
        }
      }
    },
    "/api/Horarios": {
      "get": {
        "tags": [
          "Horarios"
        ],
        "responses": {
          "200": {
            "description": "OK"
          }
        }
      },
      "post": {
        "tags": [
          "Horarios"
        ],
        "requestBody": {
          "content": {
            "application/json": {
              "schema": {
                "$ref": "#/components/schemas/HorariosCreateDto"
              }
            },
            "text/json": {
              "schema": {
                "$ref": "#/components/schemas/HorariosCreateDto"
              }
            },
            "application/*+json": {
              "schema": {
                "$ref": "#/components/schemas/HorariosCreateDto"
              }
            }
          }
        },
        "responses": {
          "200": {
            "description": "OK"
          }
        }
      }
    },
    "/api/Horarios/{id}": {
      "get": {
        "tags": [
          "Horarios"
        ],
        "parameters": [
          {
            "name": "id",
            "in": "path",
            "required": true,
            "schema": {
              "type": "integer",
              "format": "int32"
            }
          }
        ],
        "responses": {
          "200": {
            "description": "OK"
          }
        }
      },
      "put": {
        "tags": [
          "Horarios"
        ],
        "parameters": [
          {
            "name": "id",
            "in": "path",
            "required": true,
            "schema": {
              "type": "integer",
              "format": "int32"
            }
          }
        ],
        "requestBody": {
          "content": {
            "application/json": {
              "schema": {
                "$ref": "#/components/schemas/HorarioPutBody"
              }
            },
            "text/json": {
              "schema": {
                "$ref": "#/components/schemas/HorarioPutBody"
              }
            },
            "application/*+json": {
              "schema": {
                "$ref": "#/components/schemas/HorarioPutBody"
              }
            }
          }
        },
        "responses": {
          "200": {
            "description": "OK"
          }
        }
      },
      "delete": {
        "tags": [
          "Horarios"
        ],
        "parameters": [
          {
            "name": "id",
            "in": "path",
            "required": true,
            "schema": {
              "type": "integer",
              "format": "int32"
            }
          }
        ],
        "responses": {
          "200": {
            "description": "OK"
          }
        }
      }
    },
    "/api/Horarios/PorGrupo/{id_grupo}": {
      "get": {
        "tags": [
          "Horarios"
        ],
        "parameters": [
          {
            "name": "id_grupo",
            "in": "path",
            "required": true,
            "schema": {
              "type": "integer",
              "format": "int32"
            }
          }
        ],
        "responses": {
          "200": {
            "description": "OK"
          }
        }
      }
    },
    "/api/Materia": {
      "get": {
        "tags": [
          "Materia"
        ],
        "responses": {
          "200": {
            "description": "OK"
          }
        }
      },
      "post": {
        "tags": [
          "Materia"
        ],
        "requestBody": {
          "content": {
            "application/json": {
              "schema": {
                "$ref": "#/components/schemas/MateriaCreateDto"
              }
            },
            "text/json": {
              "schema": {
                "$ref": "#/components/schemas/MateriaCreateDto"
              }
            },
            "application/*+json": {
              "schema": {
                "$ref": "#/components/schemas/MateriaCreateDto"
              }
            }
          }
        },
        "responses": {
          "200": {
            "description": "OK"
          }
        }
      }
    },
    "/api/Materia/{id}": {
      "get": {
        "tags": [
          "Materia"
        ],
        "parameters": [
          {
            "name": "id",
            "in": "path",
            "required": true,
            "schema": {
              "type": "integer",
              "format": "int32"
            }
          }
        ],
        "responses": {
          "200": {
            "description": "OK"
          }
        }
      },
      "put": {
        "tags": [
          "Materia"
        ],
        "parameters": [
          {
            "name": "id",
            "in": "path",
            "required": true,
            "schema": {
              "type": "integer",
              "format": "int32"
            }
          }
        ],
        "requestBody": {
          "content": {
            "application/json": {
              "schema": {
                "$ref": "#/components/schemas/Materia"
              }
            },
            "text/json": {
              "schema": {
                "$ref": "#/components/schemas/Materia"
              }
            },
            "application/*+json": {
              "schema": {
                "$ref": "#/components/schemas/Materia"
              }
            }
          }
        },
        "responses": {
          "200": {
            "description": "OK"
          }
        }
      },
      "delete": {
        "tags": [
          "Materia"
        ],
        "parameters": [
          {
            "name": "id",
            "in": "path",
            "required": true,
            "schema": {
              "type": "integer",
              "format": "int32"
            }
          }
        ],
        "responses": {
          "200": {
            "description": "OK"
          }
        }
      }
    },
    "/api/Matriculas": {
      "get": {
        "tags": [
          "Matriculas"
        ],
        "responses": {
          "200": {
            "description": "OK"
          }
        }
      },
      "post": {
        "tags": [
          "Matriculas"
        ],
        "requestBody": {
          "content": {
            "application/json": {
              "schema": {
                "$ref": "#/components/schemas/MatriculaCreateDto"
              }
            },
            "text/json": {
              "schema": {
                "$ref": "#/components/schemas/MatriculaCreateDto"
              }
            },
            "application/*+json": {
              "schema": {
                "$ref": "#/components/schemas/MatriculaCreateDto"
              }
            }
          }
        },
        "responses": {
          "200": {
            "description": "OK"
          }
        }
      }
    },
    "/api/Matriculas/{id}": {
      "get": {
        "tags": [
          "Matriculas"
        ],
        "parameters": [
          {
            "name": "id",
            "in": "path",
            "required": true,
            "schema": {
              "type": "integer",
              "format": "int32"
            }
          }
        ],
        "responses": {
          "200": {
            "description": "OK"
          }
        }
      },
      "put": {
        "tags": [
          "Matriculas"
        ],
        "parameters": [
          {
            "name": "id",
            "in": "path",
            "required": true,
            "schema": {
              "type": "integer",
              "format": "int32"
            }
          }
        ],
        "requestBody": {
          "content": {
            "application/json": {
              "schema": {
                "$ref": "#/components/schemas/Matricula"
              }
            },
            "text/json": {
              "schema": {
                "$ref": "#/components/schemas/Matricula"
              }
            },
            "application/*+json": {
              "schema": {
                "$ref": "#/components/schemas/Matricula"
              }
            }
          }
        },
        "responses": {
          "200": {
            "description": "OK"
          }
        }
      },
      "delete": {
        "tags": [
          "Matriculas"
        ],
        "parameters": [
          {
            "name": "id",
            "in": "path",
            "required": true,
            "schema": {
              "type": "integer",
              "format": "int32"
            }
          }
        ],
        "responses": {
          "200": {
            "description": "OK"
          }
        }
      }
    },
    "/api/Matriculas/Estudiante/{id_estudiante}": {
      "get": {
        "tags": [
          "Matriculas"
        ],
        "parameters": [
          {
            "name": "id_estudiante",
            "in": "path",
            "required": true,
            "schema": {
              "type": "integer",
              "format": "int32"
            }
          }
        ],
        "responses": {
          "200": {
            "description": "OK"
          }
        }
      }
    },
    "/api/Matriculas/Periodo/{id_periodo}": {
      "get": {
        "tags": [
          "Matriculas"
        ],
        "parameters": [
          {
            "name": "id_periodo",
            "in": "path",
            "required": true,
            "schema": {
              "type": "integer",
              "format": "int32"
            }
          }
        ],
        "responses": {
          "200": {
            "description": "OK"
          }
        }
      }
    },
    "/api/Pagos": {
      "get": {
        "tags": [
          "Pagos"
        ],
        "responses": {
          "200": {
            "description": "OK"
          }
        }
      },
      "post": {
        "tags": [
          "Pagos"
        ],
        "requestBody": {
          "content": {
            "application/json": {
              "schema": {
                "$ref": "#/components/schemas/PagosCreateDto"
              }
            },
            "text/json": {
              "schema": {
                "$ref": "#/components/schemas/PagosCreateDto"
              }
            },
            "application/*+json": {
              "schema": {
                "$ref": "#/components/schemas/PagosCreateDto"
              }
            }
          }
        },
        "responses": {
          "200": {
            "description": "OK"
          }
        }
      }
    },
    "/api/Pagos/{id}": {
      "get": {
        "tags": [
          "Pagos"
        ],
        "parameters": [
          {
            "name": "id",
            "in": "path",
            "required": true,
            "schema": {
              "type": "integer",
              "format": "int32"
            }
          }
        ],
        "responses": {
          "200": {
            "description": "OK"
          }
        }
      },
      "put": {
        "tags": [
          "Pagos"
        ],
        "parameters": [
          {
            "name": "id",
            "in": "path",
            "required": true,
            "schema": {
              "type": "integer",
              "format": "int32"
            }
          }
        ],
        "requestBody": {
          "content": {
            "application/json": {
              "schema": {
                "$ref": "#/components/schemas/PagoPutBody"
              }
            },
            "text/json": {
              "schema": {
                "$ref": "#/components/schemas/PagoPutBody"
              }
            },
            "application/*+json": {
              "schema": {
                "$ref": "#/components/schemas/PagoPutBody"
              }
            }
          }
        },
        "responses": {
          "200": {
            "description": "OK"
          }
        }
      },
      "delete": {
        "tags": [
          "Pagos"
        ],
        "parameters": [
          {
            "name": "id",
            "in": "path",
            "required": true,
            "schema": {
              "type": "integer",
              "format": "int32"
            }
          }
        ],
        "responses": {
          "200": {
            "description": "OK"
          }
        }
      }
    },
    "/api/Pagos/PorEstudiante/{id_estudiante}": {
      "get": {
        "tags": [
          "Pagos"
        ],
        "parameters": [
          {
            "name": "id_estudiante",
            "in": "path",
            "required": true,
            "schema": {
              "type": "integer",
              "format": "int32"
            }
          }
        ],
        "responses": {
          "200": {
            "description": "OK"
          }
        }
      }
    },
    "/api/Pagos/PorEstado/{estado}": {
      "get": {
        "tags": [
          "Pagos"
        ],
        "parameters": [
          {
            "name": "estado",
            "in": "path",
            "required": true,
            "schema": {
              "type": "string"
            }
          }
        ],
        "responses": {
          "200": {
            "description": "OK"
          }
        }
      }
    },
    "/api/Pagos/PorFechas": {
      "get": {
        "tags": [
          "Pagos"
        ],
        "parameters": [
          {
            "name": "desde",
            "in": "query",
            "schema": {
              "type": "string",
              "format": "date-time"
            }
          },
          {
            "name": "hasta",
            "in": "query",
            "schema": {
              "type": "string",
              "format": "date-time"
            }
          }
        ],
        "responses": {
          "200": {
            "description": "OK"
          }
        }
      }
    },
    "/api/Pagos/{id}/estado": {
      "patch": {
        "tags": [
          "Pagos"
        ],
        "parameters": [
          {
            "name": "id",
            "in": "path",
            "required": true,
            "schema": {
              "type": "integer",
              "format": "int32"
            }
          }
        ],
        "requestBody": {
          "content": {
            "application/json": {
              "schema": {
                "$ref": "#/components/schemas/CambiarEstadoDto"
              }
            },
            "text/json": {
              "schema": {
                "$ref": "#/components/schemas/CambiarEstadoDto"
              }
            },
            "application/*+json": {
              "schema": {
                "$ref": "#/components/schemas/CambiarEstadoDto"
              }
            }
          }
        },
        "responses": {
          "200": {
            "description": "OK"
          }
        }
      }
    },
    "/api/Periodo_Lectivo": {
      "get": {
        "tags": [
          "Periodo_Lectivo"
        ],
        "responses": {
          "200": {
            "description": "OK"
          }
        }
      },
      "post": {
        "tags": [
          "Periodo_Lectivo"
        ],
        "requestBody": {
          "content": {
            "application/json": {
              "schema": {
                "$ref": "#/components/schemas/Periodo_LectivoCreateDto"
              }
            },
            "text/json": {
              "schema": {
                "$ref": "#/components/schemas/Periodo_LectivoCreateDto"
              }
            },
            "application/*+json": {
              "schema": {
                "$ref": "#/components/schemas/Periodo_LectivoCreateDto"
              }
            }
          }
        },
        "responses": {
          "200": {
            "description": "OK"
          }
        }
      }
    },
    "/api/Periodo_Lectivo/{id}": {
      "get": {
        "tags": [
          "Periodo_Lectivo"
        ],
        "parameters": [
          {
            "name": "id",
            "in": "path",
            "required": true,
            "schema": {
              "type": "integer",
              "format": "int32"
            }
          }
        ],
        "responses": {
          "200": {
            "description": "OK"
          }
        }
      },
      "put": {
        "tags": [
          "Periodo_Lectivo"
        ],
        "parameters": [
          {
            "name": "id",
            "in": "path",
            "required": true,
            "schema": {
              "type": "integer",
              "format": "int32"
            }
          }
        ],
        "requestBody": {
          "content": {
            "application/json": {
              "schema": {
                "$ref": "#/components/schemas/Periodo_Lectivo"
              }
            },
            "text/json": {
              "schema": {
                "$ref": "#/components/schemas/Periodo_Lectivo"
              }
            },
            "application/*+json": {
              "schema": {
                "$ref": "#/components/schemas/Periodo_Lectivo"
              }
            }
          }
        },
        "responses": {
          "200": {
            "description": "OK"
          }
        }
      },
      "delete": {
        "tags": [
          "Periodo_Lectivo"
        ],
        "parameters": [
          {
            "name": "id",
            "in": "path",
            "required": true,
            "schema": {
              "type": "integer",
              "format": "int32"
            }
          }
        ],
        "responses": {
          "200": {
            "description": "OK"
          }
        }
      }
    },
    "/api/Periodo_Lectivo/PorAnio/{anio}": {
      "get": {
        "tags": [
          "Periodo_Lectivo"
        ],
        "parameters": [
          {
            "name": "anio",
            "in": "path",
            "required": true,
            "schema": {
              "type": "integer",
              "format": "int32"
            }
          }
        ],
        "responses": {
          "200": {
            "description": "OK"
          }
        }
      }
    },
    "/api/Periodo_Lectivo/Vigente": {
      "get": {
        "tags": [
          "Periodo_Lectivo"
        ],
        "parameters": [
          {
            "name": "fecha",
            "in": "query",
            "schema": {
              "type": "string",
              "format": "date-time"
            }
          }
        ],
        "responses": {
          "200": {
            "description": "OK"
          }
        }
      }
    },
    "/api/Plan_Estudio": {
      "get": {
        "tags": [
          "Plan_Estudio"
        ],
        "responses": {
          "200": {
            "description": "OK"
          }
        }
      },
      "post": {
        "tags": [
          "Plan_Estudio"
        ],
        "requestBody": {
          "content": {
            "application/json": {
              "schema": {
                "$ref": "#/components/schemas/Plan_EstudioCreateDto"
              }
            },
            "text/json": {
              "schema": {
                "$ref": "#/components/schemas/Plan_EstudioCreateDto"
              }
            },
            "application/*+json": {
              "schema": {
                "$ref": "#/components/schemas/Plan_EstudioCreateDto"
              }
            }
          }
        },
        "responses": {
          "200": {
            "description": "OK"
          }
        }
      }
    },
    "/api/Plan_Estudio/{id}": {
      "get": {
        "tags": [
          "Plan_Estudio"
        ],
        "parameters": [
          {
            "name": "id",
            "in": "path",
            "required": true,
            "schema": {
              "type": "integer",
              "format": "int32"
            }
          }
        ],
        "responses": {
          "200": {
            "description": "OK"
          }
        }
      },
      "put": {
        "tags": [
          "Plan_Estudio"
        ],
        "parameters": [
          {
            "name": "id",
            "in": "path",
            "required": true,
            "schema": {
              "type": "integer",
              "format": "int32"
            }
          }
        ],
        "requestBody": {
          "content": {
            "application/json": {
              "schema": {
                "$ref": "#/components/schemas/Plan_Estudio"
              }
            },
            "text/json": {
              "schema": {
                "$ref": "#/components/schemas/Plan_Estudio"
              }
            },
            "application/*+json": {
              "schema": {
                "$ref": "#/components/schemas/Plan_Estudio"
              }
            }
          }
        },
        "responses": {
          "200": {
            "description": "OK"
          }
        }
      },
      "delete": {
        "tags": [
          "Plan_Estudio"
        ],
        "parameters": [
          {
            "name": "id",
            "in": "path",
            "required": true,
            "schema": {
              "type": "integer",
              "format": "int32"
            }
          }
        ],
        "responses": {
          "200": {
            "description": "OK"
          }
        }
      }
    },
    "/api/Plan_Estudio/PorCarrera/{id_carrera}": {
      "get": {
        "tags": [
          "Plan_Estudio"
        ],
        "parameters": [
          {
            "name": "id_carrera",
            "in": "path",
            "required": true,
            "schema": {
              "type": "integer",
              "format": "int32"
            }
          }
        ],
        "responses": {
          "200": {
            "description": "OK"
          }
        }
      }
    },
    "/api/Plan_Estudio/PorCarreraYAnio": {
      "get": {
        "tags": [
          "Plan_Estudio"
        ],
        "parameters": [
          {
            "name": "idCarrera",
            "in": "query",
            "schema": {
              "type": "integer",
              "format": "int32"
            }
          },
          {
            "name": "anio",
            "in": "query",
            "schema": {
              "type": "integer",
              "format": "int32"
            }
          }
        ],
        "responses": {
          "200": {
            "description": "OK"
          }
        }
      }
    },
    "/api/Profesors": {
      "get": {
        "tags": [
          "Profesors"
        ],
        "responses": {
          "200": {
            "description": "OK"
          }
        }
      },
      "post": {
        "tags": [
          "Profesors"
        ],
        "requestBody": {
          "content": {
            "application/json": {
              "schema": {
                "$ref": "#/components/schemas/ProfesorCreateDto"
              }
            },
            "text/json": {
              "schema": {
                "$ref": "#/components/schemas/ProfesorCreateDto"
              }
            },
            "application/*+json": {
              "schema": {
                "$ref": "#/components/schemas/ProfesorCreateDto"
              }
            }
          }
        },
        "responses": {
          "200": {
            "description": "OK"
          }
        }
      }
    },
    "/api/Profesors/{id}": {
      "get": {
        "tags": [
          "Profesors"
        ],
        "parameters": [
          {
            "name": "id",
            "in": "path",
            "required": true,
            "schema": {
              "type": "integer",
              "format": "int32"
            }
          }
        ],
        "responses": {
          "200": {
            "description": "OK"
          }
        }
      },
      "put": {
        "tags": [
          "Profesors"
        ],
        "parameters": [
          {
            "name": "id",
            "in": "path",
            "required": true,
            "schema": {
              "type": "integer",
              "format": "int32"
            }
          }
        ],
        "requestBody": {
          "content": {
            "application/json": {
              "schema": {
                "$ref": "#/components/schemas/Profesor"
              }
            },
            "text/json": {
              "schema": {
                "$ref": "#/components/schemas/Profesor"
              }
            },
            "application/*+json": {
              "schema": {
                "$ref": "#/components/schemas/Profesor"
              }
            }
          }
        },
        "responses": {
          "200": {
            "description": "OK"
          }
        }
      },
      "delete": {
        "tags": [
          "Profesors"
        ],
        "parameters": [
          {
            "name": "id",
            "in": "path",
            "required": true,
            "schema": {
              "type": "integer",
              "format": "int32"
            }
          }
        ],
        "responses": {
          "200": {
            "description": "OK"
          }
        }
      }
    },
    "/api/Requisitos": {
      "get": {
        "tags": [
          "Requisitos"
        ],
        "responses": {
          "200": {
            "description": "OK"
          }
        }
      },
      "post": {
        "tags": [
          "Requisitos"
        ],
        "requestBody": {
          "content": {
            "application/json": {
              "schema": {
                "$ref": "#/components/schemas/RequisitosCreateDto"
              }
            },
            "text/json": {
              "schema": {
                "$ref": "#/components/schemas/RequisitosCreateDto"
              }
            },
            "application/*+json": {
              "schema": {
                "$ref": "#/components/schemas/RequisitosCreateDto"
              }
            }
          }
        },
        "responses": {
          "200": {
            "description": "OK"
          }
        }
      }
    },
    "/api/Requisitos/{id_materia}/{id_requisito}": {
      "get": {
        "tags": [
          "Requisitos"
        ],
        "parameters": [
          {
            "name": "id_materia",
            "in": "path",
            "required": true,
            "schema": {
              "type": "integer",
              "format": "int32"
            }
          },
          {
            "name": "id_requisito",
            "in": "path",
            "required": true,
            "schema": {
              "type": "integer",
              "format": "int32"
            }
          }
        ],
        "responses": {
          "200": {
            "description": "OK"
          }
        }
      },
      "put": {
        "tags": [
          "Requisitos"
        ],
        "parameters": [
          {
            "name": "id_materia",
            "in": "path",
            "required": true,
            "schema": {
              "type": "integer",
              "format": "int32"
            }
          },
          {
            "name": "id_requisito",
            "in": "path",
            "required": true,
            "schema": {
              "type": "integer",
              "format": "int32"
            }
          }
        ],
        "requestBody": {
          "content": {
            "application/json": {
              "schema": {
                "$ref": "#/components/schemas/Requisito"
              }
            },
            "text/json": {
              "schema": {
                "$ref": "#/components/schemas/Requisito"
              }
            },
            "application/*+json": {
              "schema": {
                "$ref": "#/components/schemas/Requisito"
              }
            }
          }
        },
        "responses": {
          "200": {
            "description": "OK"
          }
        }
      },
      "delete": {
        "tags": [
          "Requisitos"
        ],
        "parameters": [
          {
            "name": "id_materia",
            "in": "path",
            "required": true,
            "schema": {
              "type": "integer",
              "format": "int32"
            }
          },
          {
            "name": "id_requisito",
            "in": "path",
            "required": true,
            "schema": {
              "type": "integer",
              "format": "int32"
            }
          }
        ],
        "responses": {
          "200": {
            "description": "OK"
          }
        }
      }
    },
    "/api/Requisitos/PorMateria/{id_materia}": {
      "get": {
        "tags": [
          "Requisitos"
        ],
        "parameters": [
          {
            "name": "id_materia",
            "in": "path",
            "required": true,
            "schema": {
              "type": "integer",
              "format": "int32"
            }
          }
        ],
        "responses": {
          "200": {
            "description": "OK"
          }
        }
      }
    },
    "/api/Requisitos/PorRequisito/{id_requisito}": {
      "get": {
        "tags": [
          "Requisitos"
        ],
        "parameters": [
          {
            "name": "id_requisito",
            "in": "path",
            "required": true,
            "schema": {
              "type": "integer",
              "format": "int32"
            }
          }
        ],
        "responses": {
          "200": {
            "description": "OK"
          }
        }
      }
    },
    "/api/Roles": {
      "get": {
        "tags": [
          "Roles"
        ],
        "responses": {
          "200": {
            "description": "OK"
          }
        }
      },
      "post": {
        "tags": [
          "Roles"
        ],
        "requestBody": {
          "content": {
            "application/json": {
              "schema": {
                "$ref": "#/components/schemas/RolesCreateDto"
              }
            },
            "text/json": {
              "schema": {
                "$ref": "#/components/schemas/RolesCreateDto"
              }
            },
            "application/*+json": {
              "schema": {
                "$ref": "#/components/schemas/RolesCreateDto"
              }
            }
          }
        },
        "responses": {
          "200": {
            "description": "OK"
          }
        }
      }
    },
    "/api/Roles/{id}": {
      "get": {
        "tags": [
          "Roles"
        ],
        "parameters": [
          {
            "name": "id",
            "in": "path",
            "required": true,
            "schema": {
              "type": "integer",
              "format": "int32"
            }
          }
        ],
        "responses": {
          "200": {
            "description": "OK"
          }
        }
      },
      "put": {
        "tags": [
          "Roles"
        ],
        "parameters": [
          {
            "name": "id",
            "in": "path",
            "required": true,
            "schema": {
              "type": "integer",
              "format": "int32"
            }
          }
        ],
        "requestBody": {
          "content": {
            "application/json": {
              "schema": {
                "$ref": "#/components/schemas/Rol"
              }
            },
            "text/json": {
              "schema": {
                "$ref": "#/components/schemas/Rol"
              }
            },
            "application/*+json": {
              "schema": {
                "$ref": "#/components/schemas/Rol"
              }
            }
          }
        },
        "responses": {
          "200": {
            "description": "OK"
          }
        }
      },
      "delete": {
        "tags": [
          "Roles"
        ],
        "parameters": [
          {
            "name": "id",
            "in": "path",
            "required": true,
            "schema": {
              "type": "integer",
              "format": "int32"
            }
          }
        ],
        "responses": {
          "200": {
            "description": "OK"
          }
        }
      }
    },
    "/api/Usuario/datos-profesor/{idUsuario}": {
      "get": {
        "tags": [
          "Usuario"
        ],
        "parameters": [
          {
            "name": "idUsuario",
            "in": "path",
            "required": true,
            "schema": {
              "type": "integer",
              "format": "int32"
            }
          }
        ],
        "responses": {
          "200": {
            "description": "OK"
          }
        }
      }
    },
    "/api/Usuario/estudiantes/activos": {
      "get": {
        "tags": [
          "Usuario"
        ],
        "responses": {
          "200": {
            "description": "OK"
          }
        }
      }
    },
    "/api/Usuario": {
      "get": {
        "tags": [
          "Usuario"
        ],
        "responses": {
          "200": {
            "description": "OK"
          }
        }
      },
      "post": {
        "tags": [
          "Usuario"
        ],
        "requestBody": {
          "content": {
            "application/json": {
              "schema": {
                "$ref": "#/components/schemas/UsuarioCreateDto"
              }
            },
            "text/json": {
              "schema": {
                "$ref": "#/components/schemas/UsuarioCreateDto"
              }
            },
            "application/*+json": {
              "schema": {
                "$ref": "#/components/schemas/UsuarioCreateDto"
              }
            }
          }
        },
        "responses": {
          "200": {
            "description": "OK"
          }
        }
      }
    },
    "/api/Usuario/{id}": {
      "get": {
        "tags": [
          "Usuario"
        ],
        "parameters": [
          {
            "name": "id",
            "in": "path",
            "required": true,
            "schema": {
              "type": "integer",
              "format": "int32"
            }
          }
        ],
        "responses": {
          "200": {
            "description": "OK"
          }
        }
      },
      "put": {
        "tags": [
          "Usuario"
        ],
        "parameters": [
          {
            "name": "id",
            "in": "path",
            "required": true,
            "schema": {
              "type": "integer",
              "format": "int32"
            }
          }
        ],
        "requestBody": {
          "content": {
            "application/json": {
              "schema": {
                "$ref": "#/components/schemas/Usuario"
              }
            },
            "text/json": {
              "schema": {
                "$ref": "#/components/schemas/Usuario"
              }
            },
            "application/*+json": {
              "schema": {
                "$ref": "#/components/schemas/Usuario"
              }
            }
          }
        },
        "responses": {
          "200": {
            "description": "OK"
          }
        }
      },
      "delete": {
        "tags": [
          "Usuario"
        ],
        "parameters": [
          {
            "name": "id",
            "in": "path",
            "required": true,
            "schema": {
              "type": "integer",
              "format": "int32"
            }
          }
        ],
        "responses": {
          "200": {
            "description": "OK"
          }
        }
      }
    },
    "/api/Usuario/actualizar-profesor/{idUsuario}": {
      "put": {
        "tags": [
          "Usuario"
        ],
        "parameters": [
          {
            "name": "idUsuario",
            "in": "path",
            "required": true,
            "schema": {
              "type": "integer",
              "format": "int32"
            }
          }
        ],
        "requestBody": {
          "content": {
            "application/json": {
              "schema": {
                "$ref": "#/components/schemas/ActualizarProfesorDto"
              }
            },
            "text/json": {
              "schema": {
                "$ref": "#/components/schemas/ActualizarProfesorDto"
              }
            },
            "application/*+json": {
              "schema": {
                "$ref": "#/components/schemas/ActualizarProfesorDto"
              }
            }
          }
        },
        "responses": {
          "200": {
            "description": "OK"
          }
        }
      }
    },
    "/api/Usuario/actualizar/{idUsuario}": {
      "put": {
        "tags": [
          "Usuario"
        ],
        "parameters": [
          {
            "name": "idUsuario",
            "in": "path",
            "required": true,
            "schema": {
              "type": "integer",
              "format": "int32"
            }
          }
        ],
        "requestBody": {
          "content": {
            "application/json": {
              "schema": {
                "$ref": "#/components/schemas/ActualizarProfesorDto"
              }
            },
            "text/json": {
              "schema": {
                "$ref": "#/components/schemas/ActualizarProfesorDto"
              }
            },
            "application/*+json": {
              "schema": {
                "$ref": "#/components/schemas/ActualizarProfesorDto"
              }
            }
          }
        },
        "responses": {
          "200": {
            "description": "OK"
          }
        }
      }
    },
    "/api/Usuario/login": {
      "post": {
        "tags": [
          "Usuario"
        ],
        "requestBody": {
          "content": {
            "application/json": {
              "schema": {
                "$ref": "#/components/schemas/UsuarioLoginDto"
              }
            },
            "text/json": {
              "schema": {
                "$ref": "#/components/schemas/UsuarioLoginDto"
              }
            },
            "application/*+json": {
              "schema": {
                "$ref": "#/components/schemas/UsuarioLoginDto"
              }
            }
          }
        },
        "responses": {
          "200": {
            "description": "OK"
          }
        }
      }
    },
    "/api/Usuario/inactivos": {
      "get": {
        "tags": [
          "Usuario"
        ],
        "responses": {
          "200": {
            "description": "OK"
          }
        }
      }
    },
    "/api/Usuario/cambiar-estado/{id}": {
      "put": {
        "tags": [
          "Usuario"
        ],
        "parameters": [
          {
            "name": "id",
            "in": "path",
            "required": true,
            "schema": {
              "type": "integer",
              "format": "int32"
            }
          }
        ],
        "requestBody": {
          "content": {
            "application/json": {
              "schema": {
                "type": "boolean"
              }
            },
            "text/json": {
              "schema": {
                "type": "boolean"
              }
            },
            "application/*+json": {
              "schema": {
                "type": "boolean"
              }
            }
          }
        },
        "responses": {
          "200": {
            "description": "OK"
          }
        }
      }
    },
    "/api/Usuario/cambiar-rol/{id}": {
      "put": {
        "tags": [
          "Usuario"
        ],
        "parameters": [
          {
            "name": "id",
            "in": "path",
            "required": true,
            "schema": {
              "type": "integer",
              "format": "int32"
            }
          }
        ],
        "requestBody": {
          "content": {
            "application/json": {
              "schema": {
                "type": "integer",
                "format": "int32"
              }
            },
            "text/json": {
              "schema": {
                "type": "integer",
                "format": "int32"
              }
            },
            "application/*+json": {
              "schema": {
                "type": "integer",
                "format": "int32"
              }
            }
          }
        },
        "responses": {
          "200": {
            "description": "OK"
          }
        }
      }
    }
  },
  "components": {
    "schemas": {
      "ActualizarProfesorDto": {
        "type": "object",
        "properties": {
          "nombre": {
            "type": "string",
            "nullable": true
          },
          "email": {
            "type": "string",
            "nullable": true
          },
          "cedula": {
            "type": "string",
            "nullable": true
          },
          "telefono": {
            "type": "string",
            "nullable": true
          },
          "correoPersonal": {
            "type": "string",
            "nullable": true
          }
        },
        "additionalProperties": false
      },
      "Asistencia": {
        "type": "object",
        "properties": {
          "idAsistencia": {
            "type": "integer",
            "format": "int32"
          },
          "idGrupo": {
            "type": "integer",
            "format": "int32"
          },
          "idProfesor": {
            "type": "integer",
            "format": "int32"
          },
          "idEstudiante": {
            "type": "integer",
            "format": "int32"
          },
          "eAsistencia": {
            "type": "boolean"
          },
          "fecha": {
            "type": "string",
            "format": "date-time"
          },
          "grupo": {
            "$ref": "#/components/schemas/Grupo"
          },
          "profesor": {
            "$ref": "#/components/schemas/Profesor"
          },
          "estudiante": {
            "$ref": "#/components/schemas/Estudiante"
          }
        },
        "additionalProperties": false
      },
      "AsistenciaCreateDto": {
        "type": "object",
        "properties": {
          "idGrupo": {
            "type": "integer",
            "format": "int32"
          },
          "idProfesor": {
            "type": "integer",
            "format": "int32"
          },
          "idEstudiante": {
            "type": "integer",
            "format": "int32"
          },
          "eAsistencia": {
            "type": "boolean"
          },
          "fecha": {
            "type": "string",
            "format": "date-time",
            "nullable": true
          }
        },
        "additionalProperties": false
      },
      "BitacoraCreateDto": {
        "type": "object",
        "properties": {
          "idUsuario": {
            "type": "integer",
            "format": "int32"
          },
          "accion": {
            "type": "string",
            "nullable": true
          },
          "fechaHora": {
            "type": "string",
            "format": "date-time",
            "nullable": true
          },
          "ip": {
            "type": "string",
            "nullable": true
          }
        },
        "additionalProperties": false
      },
      "CambiarEstadoDto": {
        "type": "object",
        "properties": {
          "estado": {
            "type": "string",
            "nullable": true
          }
        },
        "additionalProperties": false
      },
      "Carrera": {
        "type": "object",
        "properties": {
          "idCarrera": {
            "type": "integer",
            "format": "int32"
          },
          "nombreCarrera": {
            "type": "string",
            "nullable": true
          }
        },
        "additionalProperties": false
      },
      "CarreraCreateDto": {
        "type": "object",
        "properties": {
          "nombreCarrera": {
            "type": "string",
            "nullable": true
          }
        },
        "additionalProperties": false
      },
      "CitaMatriculaCreateDto": {
        "type": "object",
        "properties": {
          "idEstudiante": {
            "type": "integer",
            "format": "int32"
          },
          "idPeriodo": {
            "type": "integer",
            "format": "int32"
          },
          "fechaHora": {
            "type": "string",
            "format": "date-time"
          }
        },
        "additionalProperties": false
      },
      "Cita_Matricula": {
        "type": "object",
        "properties": {
          "idCita": {
            "type": "integer",
            "format": "int32"
          },
          "idEstudiante": {
            "type": "integer",
            "format": "int32"
          },
          "idPeriodo": {
            "type": "integer",
            "format": "int32"
          },
          "fechaHora": {
            "type": "string",
            "format": "date-time"
          },
          "estudiante": {
            "$ref": "#/components/schemas/Estudiante"
          }
        },
        "additionalProperties": false
      },
      "Correquisito": {
        "type": "object",
        "properties": {
          "idMateria": {
            "type": "integer",
            "format": "int32"
          },
          "idCorrequisito": {
            "type": "integer",
            "format": "int32"
          },
          "materia": {
            "$ref": "#/components/schemas/Materia"
          },
          "correquisitoMateria": {
            "$ref": "#/components/schemas/Materia"
          }
        },
        "additionalProperties": false
      },
      "CorrequisitoCreateDto": {
        "type": "object",
        "properties": {
          "idMateria": {
            "type": "integer",
            "format": "int32"
          },
          "idCorrequisito": {
            "type": "integer",
            "format": "int32"
          }
        },
        "additionalProperties": false
      },
      "DetallePago": {
        "type": "object",
        "properties": {
          "idDetallePago": {
            "type": "integer",
            "format": "int32"
          },
          "idPago": {
            "type": "integer",
            "format": "int32"
          },
          "idMatricula": {
            "type": "integer",
            "format": "int32"
          },
          "pago": {
            "$ref": "#/components/schemas/Pago"
          },
          "matricula": {
            "$ref": "#/components/schemas/Matricula"
          }
        },
        "additionalProperties": false
      },
      "Detalle_Matricula": {
        "type": "object",
        "properties": {
          "idDetalle": {
            "type": "integer",
            "format": "int32"
          },
          "idMatricula": {
            "type": "integer",
            "format": "int32"
          },
          "idGrupo": {
            "type": "integer",
            "format": "int32"
          },
          "nota": {
            "type": "number",
            "format": "double"
          },
          "condicion": {
            "type": "string",
            "nullable": true
          },
          "matricula": {
            "$ref": "#/components/schemas/Matricula"
          },
          "grupo": {
            "$ref": "#/components/schemas/Grupo"
          }
        },
        "additionalProperties": false
      },
      "Detalle_MatriculaCreateDto": {
        "type": "object",
        "properties": {
          "idMatricula": {
            "type": "integer",
            "format": "int32"
          },
          "idGrupo": {
            "type": "integer",
            "format": "int32"
          },
          "nota": {
            "type": "number",
            "format": "double"
          },
          "condicion": {
            "type": "string",
            "nullable": true
          }
        },
        "additionalProperties": false
      },
      "Detalle_PagosCreateDto": {
        "type": "object",
        "properties": {
          "id_pago": {
            "type": "integer",
            "format": "int32"
          },
          "id_matricula": {
            "type": "integer",
            "format": "int32"
          }
        },
        "additionalProperties": false
      },
      "Estudiante": {
        "type": "object",
        "properties": {
          "idEstudiante": {
            "type": "integer",
            "format": "int32"
          },
          "idUsuario": {
            "type": "integer",
            "format": "int32"
          },
          "carnet": {
            "type": "string",
            "nullable": true
          },
          "telefono": {
            "type": "string",
            "nullable": true
          },
          "direccion": {
            "type": "string",
            "nullable": true
          },
          "idCarrera": {
            "type": "integer",
            "format": "int32",
            "nullable": true
          },
          "usuario": {
            "$ref": "#/components/schemas/Usuario"
          }
        },
        "additionalProperties": false
      },
      "EstudianteCreateDto": {
        "type": "object",
        "properties": {
          "idUsuario": {
            "type": "integer",
            "format": "int32"
          },
          "nombre": {
            "type": "string",
            "nullable": true
          },
          "carnet": {
            "type": "string",
            "nullable": true
          },
          "telefono": {
            "type": "string",
            "nullable": true
          },
          "direccion": {
            "type": "string",
            "nullable": true
          },
          "idCarrera": {
            "type": "integer",
            "format": "int32",
            "nullable": true
          },
          "usuario": {
            "$ref": "#/components/schemas/Usuario"
          }
        },
        "additionalProperties": false
      },
      "EstudianteMini": {
        "type": "object",
        "properties": {
          "idEstudiante": {
            "type": "integer",
            "format": "int32"
          },
          "carnet": {
            "type": "string",
            "nullable": true
          },
          "telefono": {
            "type": "string",
            "nullable": true
          }
        },
        "additionalProperties": false
      },
      "Grupo": {
        "type": "object",
        "properties": {
          "idGrupo": {
            "type": "integer",
            "format": "int32"
          },
          "idMateria": {
            "type": "integer",
            "format": "int32"
          },
          "idProfesor": {
            "type": "integer",
            "format": "int32"
          },
          "grupoNumero": {
            "type": "string",
            "nullable": true
          },
          "aula": {
            "type": "string",
            "nullable": true
          },
          "cupoMax": {
            "type": "integer",
            "format": "int32"
          },
          "materia": {
            "$ref": "#/components/schemas/Materia"
          },
          "profesor": {
            "$ref": "#/components/schemas/Profesor"
          }
        },
        "additionalProperties": false
      },
      "GrupoMiniPut": {
        "type": "object",
        "properties": {
          "idGrupo": {
            "type": "integer",
            "format": "int32"
          },
          "idMateria": {
            "type": "integer",
            "format": "int32"
          },
          "idProfesor": {
            "type": "integer",
            "format": "int32"
          },
          "grupoNumero": {
            "type": "string",
            "nullable": true
          },
          "aula": {
            "type": "string",
            "nullable": true
          },
          "cupoMax": {
            "type": "integer",
            "format": "int32"
          }
        },
        "additionalProperties": false
      },
      "GrupoPutBody": {
        "type": "object",
        "properties": {
          "idGrupo": {
            "type": "integer",
            "format": "int32"
          },
          "idMateria": {
            "type": "integer",
            "format": "int32"
          },
          "idProfesor": {
            "type": "integer",
            "format": "int32"
          },
          "grupoNumero": {
            "type": "string",
            "nullable": true
          },
          "aula": {
            "type": "string",
            "nullable": true
          },
          "cupoMax": {
            "type": "integer",
            "format": "int32"
          },
          "materia": {
            "$ref": "#/components/schemas/MateriaMiniPut"
          }
        },
        "additionalProperties": false
      },
      "GruposCreateDto": {
        "type": "object",
        "properties": {
          "id_materia": {
            "type": "integer",
            "format": "int32"
          },
          "id_profesor": {
            "type": "integer",
            "format": "int32"
          },
          "grupo_numero": {
            "type": "string",
            "nullable": true
          },
          "aula": {
            "type": "string",
            "nullable": true
          },
          "cupo_max": {
            "type": "integer",
            "format": "int32"
          }
        },
        "additionalProperties": false
      },
      "HorarioPutBody": {
        "type": "object",
        "properties": {
          "idHorario": {
            "type": "integer",
            "format": "int32"
          },
          "idGrupo": {
            "type": "integer",
            "format": "int32"
          },
          "diaSemana": {
            "type": "string",
            "nullable": true
          },
          "horaInicio": {
            "type": "string",
            "format": "date-span"
          },
          "horaFin": {
            "type": "string",
            "format": "date-span"
          },
          "grupo": {
            "$ref": "#/components/schemas/GrupoMiniPut"
          }
        },
        "additionalProperties": false
      },
      "HorariosCreateDto": {
        "type": "object",
        "properties": {
          "id_grupo": {
            "type": "integer",
            "format": "int32"
          },
          "dia_semana": {
            "type": "string",
            "nullable": true
          },
          "hora_inicio": {
            "type": "string",
            "format": "date-span"
          },
          "hora_fin": {
            "type": "string",
            "format": "date-span"
          }
        },
        "additionalProperties": false
      },
      "Materia": {
        "type": "object",
        "properties": {
          "idMateria": {
            "type": "integer",
            "format": "int32"
          },
          "codigo": {
            "type": "string",
            "nullable": true
          },
          "nombre": {
            "type": "string",
            "nullable": true
          },
          "creditos": {
            "type": "integer",
            "format": "int32"
          },
          "idPlan": {
            "type": "integer",
            "format": "int32",
            "nullable": true
          },
          "planEstudio": {
            "$ref": "#/components/schemas/Plan_Estudio"
          }
        },
        "additionalProperties": false
      },
      "MateriaCreateDto": {
        "type": "object",
        "properties": {
          "idMateria": {
            "type": "integer",
            "format": "int32"
          },
          "codigo": {
            "type": "string",
            "nullable": true
          },
          "nombre": {
            "type": "string",
            "nullable": true
          },
          "creditos": {
            "type": "integer",
            "format": "int32"
          },
          "idPlan": {
            "type": "integer",
            "format": "int32",
            "nullable": true
          }
        },
        "additionalProperties": false
      },
      "MateriaMiniPut": {
        "type": "object",
        "properties": {
          "idMateria": {
            "type": "integer",
            "format": "int32"
          },
          "codigo": {
            "type": "string",
            "nullable": true
          },
          "nombre": {
            "type": "string",
            "nullable": true
          },
          "creditos": {
            "type": "integer",
            "format": "int32"
          },
          "idPlan": {
            "type": "integer",
            "format": "int32",
            "nullable": true
          }
        },
        "additionalProperties": false
      },
      "Matricula": {
        "type": "object",
        "properties": {
          "id_matricula": {
            "type": "integer",
            "format": "int32"
          },
          "id_estudiante": {
            "type": "integer",
            "format": "int32"
          },
          "id_periodo": {
            "type": "integer",
            "format": "int32"
          },
          "estado": {
            "type": "string",
            "nullable": true
          }
        },
        "additionalProperties": false
      },
      "MatriculaCreateDto": {
        "type": "object",
        "properties": {
          "id_estudiante": {
            "type": "integer",
            "format": "int32"
          },
          "id_periodo": {
            "type": "integer",
            "format": "int32"
          },
          "estado": {
            "type": "string",
            "nullable": true
          }
        },
        "additionalProperties": false
      },
      "Pago": {
        "type": "object",
        "properties": {
          "idPago": {
            "type": "integer",
            "format": "int32"
          },
          "idEstudiante": {
            "type": "integer",
            "format": "int32"
          },
          "monto": {
            "type": "number",
            "format": "double"
          },
          "fecha": {
            "type": "string",
            "format": "date-time"
          },
          "estado": {
            "type": "string",
            "nullable": true
          },
          "metodoPago": {
            "type": "string",
            "nullable": true
          },
          "estudiante": {
            "$ref": "#/components/schemas/Estudiante"
          }
        },
        "additionalProperties": false
      },
      "PagoPutBody": {
        "type": "object",
        "properties": {
          "idPago": {
            "type": "integer",
            "format": "int32"
          },
          "idEstudiante": {
            "type": "integer",
            "format": "int32"
          },
          "monto": {
            "type": "number",
            "format": "double"
          },
          "fecha": {
            "type": "string",
            "format": "date-time"
          },
          "estado": {
            "type": "string",
            "nullable": true
          },
          "metodoPago": {
            "type": "string",
            "nullable": true
          },
          "estudiante": {
            "$ref": "#/components/schemas/EstudianteMini"
          }
        },
        "additionalProperties": false
      },
      "PagosCreateDto": {
        "type": "object",
        "properties": {
          "id_estudiante": {
            "type": "integer",
            "format": "int32"
          },
          "monto": {
            "type": "number",
            "format": "double"
          },
          "fecha": {
            "type": "string",
            "format": "date-time"
          },
          "estado": {
            "type": "string",
            "nullable": true
          },
          "metodo_pago": {
            "type": "string",
            "nullable": true
          }
        },
        "additionalProperties": false
      },
      "Periodo_Lectivo": {
        "type": "object",
        "properties": {
          "id_periodo": {
            "type": "integer",
            "format": "int32"
          },
          "anio": {
            "type": "integer",
            "format": "int32"
          },
          "cuatrimestre": {
            "type": "string",
            "nullable": true
          },
          "fecha_inicio": {
            "type": "string",
            "format": "date-time"
          },
          "fecha_fin": {
            "type": "string",
            "format": "date-time"
          }
        },
        "additionalProperties": false
      },
      "Periodo_LectivoCreateDto": {
        "type": "object",
        "properties": {
          "anio": {
            "type": "integer",
            "format": "int32"
          },
          "cuatrimestre": {
            "type": "string",
            "nullable": true
          },
          "fecha_inicio": {
            "type": "string",
            "format": "date-time"
          },
          "fecha_fin": {
            "type": "string",
            "format": "date-time"
          }
        },
        "additionalProperties": false
      },
      "Plan_Estudio": {
        "type": "object",
        "properties": {
          "id_plan": {
            "type": "integer",
            "format": "int32"
          },
          "id_carrera": {
            "type": "integer",
            "format": "int32"
          },
          "anio_inicio": {
            "type": "integer",
            "format": "int32"
          },
          "carrera": {
            "$ref": "#/components/schemas/Carrera"
          },
          "materias": {
            "type": "array",
            "items": {
              "$ref": "#/components/schemas/Materia"
            },
            "nullable": true
          }
        },
        "additionalProperties": false
      },
      "Plan_EstudioCreateDto": {
        "type": "object",
        "properties": {
          "id_carrera": {
            "type": "integer",
            "format": "int32"
          },
          "anio_inicio": {
            "type": "integer",
            "format": "int32"
          }
        },
        "additionalProperties": false
      },
      "Profesor": {
        "type": "object",
        "properties": {
          "idProfesor": {
            "type": "integer",
            "format": "int32"
          },
          "idUsuario": {
            "type": "integer",
            "format": "int32"
          },
          "cedula": {
            "type": "string",
            "nullable": true
          },
          "telefono": {
            "type": "string",
            "nullable": true
          },
          "correoPersonal": {
            "type": "string",
            "nullable": true
          },
          "usuario": {
            "$ref": "#/components/schemas/Usuario"
          }
        },
        "additionalProperties": false
      },
      "ProfesorCreateDto": {
        "type": "object",
        "properties": {
          "idUsuario": {
            "type": "integer",
            "format": "int32"
          },
          "cedula": {
            "type": "string",
            "nullable": true
          },
          "telefono": {
            "type": "string",
            "nullable": true
          },
          "correoPersonal": {
            "type": "string",
            "nullable": true
          }
        },
        "additionalProperties": false
      },
      "Requisito": {
        "type": "object",
        "properties": {
          "idMateria": {
            "type": "integer",
            "format": "int32"
          },
          "idRequisito": {
            "type": "integer",
            "format": "int32"
          },
          "materia": {
            "$ref": "#/components/schemas/Materia"
          },
          "materiaRequisito": {
            "$ref": "#/components/schemas/Materia"
          }
        },
        "additionalProperties": false
      },
      "RequisitosCreateDto": {
        "type": "object",
        "properties": {
          "id_materia": {
            "type": "integer",
            "format": "int32"
          },
          "id_requisito": {
            "type": "integer",
            "format": "int32"
          }
        },
        "additionalProperties": false
      },
      "Rol": {
        "type": "object",
        "properties": {
          "idRol": {
            "type": "integer",
            "format": "int32"
          },
          "nombreRol": {
            "type": "string",
            "nullable": true
          },
          "usuarios": {
            "type": "array",
            "items": {
              "$ref": "#/components/schemas/Usuario"
            },
            "nullable": true
          }
        },
        "additionalProperties": false
      },
      "RolesCreateDto": {
        "type": "object",
        "properties": {
          "nombre_rol": {
            "type": "string",
            "nullable": true
          }
        },
        "additionalProperties": false
      },
      "Usuario": {
        "type": "object",
        "properties": {
          "idUsuario": {
            "type": "integer",
            "format": "int32"
          },
          "nombre": {
            "type": "string",
            "nullable": true
          },
          "email": {
            "type": "string",
            "nullable": true
          },
          "contrasena": {
            "type": "string",
            "nullable": true
          },
          "estado": {
            "type": "boolean"
          },
          "fechaCreacion": {
            "type": "string",
            "format": "date-time"
          },
          "idRol": {
            "type": "integer",
            "format": "int32"
          },
          "rol": {
            "$ref": "#/components/schemas/Rol"
          },
          "rolNombre": {
            "type": "string",
            "nullable": true
          },
          "estudiante": {
            "$ref": "#/components/schemas/Estudiante"
          },
          "profesor": {
            "$ref": "#/components/schemas/Profesor"
          }
        },
        "additionalProperties": false
      },
      "UsuarioCreateDto": {
        "type": "object",
        "properties": {
          "idUsuario": {
            "type": "integer",
            "format": "int32"
          },
          "nombre": {
            "type": "string",
            "nullable": true
          },
          "email": {
            "type": "string",
            "nullable": true
          },
          "contrasena": {
            "type": "string",
            "nullable": true
          },
          "estado": {
            "type": "boolean"
          },
          "fechaCreacion": {
            "type": "string",
            "format": "date-time"
          },
          "id_rol": {
            "type": "integer",
            "format": "int32"
          },
          "rolNombre": {
            "type": "string",
            "nullable": true
          }
        },
        "additionalProperties": false
      },
      "UsuarioLoginDto": {
        "type": "object",
        "properties": {
          "email": {
            "type": "string",
            "nullable": true
          },
          "contrasena": {
            "type": "string",
            "nullable": true
          }
        },
        "additionalProperties": false
      }
    }
  }
}